pompomp/__init__.py
pompomp/__main__.py
pompomp/cli.py
pompomp/constants.py
pompomp/core_constants.py
pompomp/exceptions.py
pompomp/meta.py
pompomp/pompomp.conf.yml
pompomp/cmd/__init__.py
pompomp/cmd/console.py
pompomp/cmd/convert.py
pompomp/cmd/generate.py
pompomp/cmd/list_templates.py
pompomp/cmd/scaffold.py
pompomp/cmd/set_meta.py
pompomp/cmd/show_icons.py
pompomp/cmd/show_palette.py
pompomp/cmd/show_schema.py
pompomp/cmd/show_vars.py
pompomp/dsl/__init__.py
pompomp/dsl/formats.py
pompomp/dsl/schema.py
pompomp/dsl/template_vars.py
pompomp/dsl/transformers.py
pompomp/dsl/handlers/__init__.py
pompomp/dsl/handlers/golang_cleaner.py
pompomp/dsl/handlers/icons.py
pompomp/dsl/handlers/ifm.py
pompomp/dsl/handlers/inc.py
pompomp/dsl/handlers/palette.py
pompomp/dsl/handlers/style_blocks.py
pompomp/dsl/handlers/ui.py
pompomp/dsl/handlers/vars.py
pompomp/helpers/__init__.py
pompomp/helpers/colors.py
pompomp/helpers/config_loader.py
pompomp/helpers/data.py
pompomp/helpers/meta.py
pompomp/helpers/scaffold.py
pompomp/helpers/validators.py
pompomp/loaders/__init__.py
pompomp/loaders/icons_loader.py
pompomp/loaders/metadata_loader.py
pompomp/loaders/palette_loader.py
pompomp/loaders/resources_loader.py
pompomp/models/__init__.py
pompomp/models/config.py
pompomp/models/icons.py
pompomp/models/meta.py
pompomp/models/palette.py
pompomp/templates/arc/meta.yml
pompomp/templates/arc/core/system/shell.yml
pompomp/templates/arc/core/system/status_code.yml
pompomp/templates/arc/core/system/sysinfo.yml
pompomp/templates/arc/core/system/time.yml
pompomp/templates/arc/core/system/os_layouts/1_line.yml
pompomp/templates/arc/core/system/os_layouts/2_lines.yml
pompomp/templates/arc/layouts/meta.yml
pompomp/templates/arc/shared/icons.yml
pompomp/templates/arc/shared/palette.yml
pompomp/templates/arc/shared/omp/os_properties.yml
pompomp/templates/arc/shared/omp/leading_diamond/execution_time_left_divider.yml
pompomp/templates/arc/shared/omp/leading_diamond/line_1_left_connector.yml
pompomp-1.0.1.dist-info/licenses/LICENSE.md
pompomp-1.0.1.dist-info/METADATA
pompomp-1.0.1.dist-info/WHEEL
pompomp-1.0.1.dist-info/entry_points.txt
pompomp-1.0.1.dist-info/top_level.txt
pompomp-1.0.1.dist-info/RECORD
