Metadata-Version: 2.4
Name: pompomp
Version: 1.0.1
Summary: Generate sleek, no-fluff themes, tailored for Oh My Posh.
Author-email: Michel TRUONG <michel.truong@gmail.com>
Maintainer-email: Michel TRUONG <michel.truong@gmail.com>
License: MIT License
Project-URL: Repository, https://github.com/KaminoU/pompomp
Project-URL: Bug Tracker, https://github.com/KaminoU/pompomp/issues
Project-URL: Documentation, https://github.com/KaminoU/pompomp/blob/main/README.md
Project-URL: Changelog, https://github.com/KaminoU/pompomp/blob/main/CHANGELOG.md
Keywords: pompomp
Classifier: Development Status :: 5 - Production/Stable
Classifier: License :: OSI Approved :: MIT License
Classifier: Programming Language :: Python :: 3
Classifier: Programming Language :: Python :: 3.12
Classifier: Operating System :: OS Independent
Classifier: Intended Audience :: Developers
Classifier: Topic :: Software Development :: Libraries :: Python Modules
License-File: LICENSE.md
Requires-Dist: build~=1.2.2
Requires-Dist: toml~=0.10.2
Requires-Dist: pydantic~=2.11.3
Requires-Dist: rich~=14.0.0
Requires-Dist: typer==0.15.3
Requires-Dist: click==8.1.8
Requires-Dist: pyyaml~=6.0.2
Requires-Dist: ruamel.yaml~=0.18.10
Dynamic: license-file
